{"boxOfficeResult": {"boxofficeType": "일별 박스오피스", "showRange": "20090608~20090608", "dailyBoxOfficeList": [{"rnum": "1", "rank": "1", "rankInten": "2", "rankOldAndNew": "OLD", "movieCd": "20090248", "movieNm": "마더", "openDt": "2009-05-28", "salesAmt": "395551000", "salesShare": "34.1", "salesInten": "-818541000", "salesChange": "-67.4", "salesAcc": "15071567500", "audiCnt": "62393", "audiInten": "-110348", "audiChange": "-63.9", "audiAcc": "2236374", "scrnCnt": "534", "showCnt": "2789"}, {"rnum": "2", "rank": "2", "rankInten": "-1", "rankOldAndNew": "OLD", "movieCd": "20090282", "movieNm": "박물관이 살아있다 2", "openDt": "2009-06-04", "salesAmt": "279906500", "salesShare": "24.1", "salesInten": "-1633411500", "salesChange": "-85.4", "salesAcc": "6231914000", "audiCnt": "44668", "audiInten": "-258406", "audiChange": "-85.3", "audiAcc": "987001", "scrnCnt": "482", "showCnt": "2823"}, {"rnum": "3", "rank": "3", "rankInten": "-1", "rankOldAndNew": "OLD", "movieCd": "20090238", "movieNm": "터미네이터 : 미래전쟁의 시작", "openDt": "2009-05-21", "salesAmt": "270370000", "salesShare": "23.3", "salesInten": "-982558500", "salesChange": "-78.4", "salesAcc": "24866216000", "audiCnt": "41995", "audiInten": "-144993", "audiChange": "-77.5", "audiAcc": "3767033", "scrnCnt": "460", "showCnt": "2563"}, {"rnum": "4", "rank": "4", "rankInten": "0", "rankOldAndNew": "OLD", "movieCd": "20090234", "movieNm": "천사와 악마", "openDt": "2009-05-14", "salesAmt": "79373500", "salesShare": "6.8", "salesInten": "-194976500", "salesChange": "-71.1", "salesAcc": "12144162000", "audiCnt": "12587", "audiInten": "-28283", "audiChange": "-69.2", "audiAcc": "1845711", "scrnCnt": "254", "showCnt": "969"}, {"rnum": "5", "rank": "5", "rankInten": "0", "rankOldAndNew": "OLD", "movieCd": "20081737", "movieNm": "7급 공무원", "openDt": "2009-04-22", "salesAmt": "65550500", "salesShare": "5.7", "salesInten": "-160325500", "salesChange": "-71", "salesAcc": "25883034000", "audiCnt": "10504", "audiInten": "-23579", "audiChange": "-69.2", "audiAcc": "3956068", "scrnCnt": "244", "showCnt": "978"}, {"rnum": "6", "rank": "6", "rankInten": "15", "rankOldAndNew": "OLD", "movieCd": "20090225", "movieNm": "인사동 스캔들", "openDt": "2009-04-29", "salesAmt": "10689000", "salesShare": "0.9", "salesInten": "9743500", "salesChange": "1030.5", "salesAcc": "7627209500", "audiCnt": "2462", "audiInten": "2329", "audiChange": "1751.1", "audiAcc": "1150902", "scrnCnt": "9", "showCnt": "24"}, {"rnum": "7", "rank": "7", "rankInten": "0", "rankOldAndNew": "OLD", "movieCd": "20090237", "movieNm": "김씨표류기", "openDt": "2009-05-14", "salesAmt": "14495500", "salesShare": "1.2", "salesInten": "-35742000", "salesChange": "-71.1", "salesAcc": "4662629500", "audiCnt": "2285", "audiInten": "-5194", "audiChange": "-69.4", "audiAcc": "710555", "scrnCnt": "133", "showCnt": "297"}, {"rnum": "8", "rank": "8", "rankInten": "0", "rankOldAndNew": "OLD", "movieCd": "20081003", "movieNm": "박쥐", "openDt": "2009-04-30", "salesAmt": "8105000", "salesShare": "0.7", "salesInten": "-9813000", "salesChange": "-54.8", "salesAcc": "14805317500", "audiCnt": "1315", "audiInten": "-1267", "audiChange": "-49.1", "audiAcc": "2200693", "scrnCnt": "67", "showCnt": "142"}, {"rnum": "9", "rank": "9", "rankInten": "-3", "rankOldAndNew": "OLD", "movieCd": "20090284", "movieNm": "코렐라인: 비밀의 문", "openDt": "2009-05-21", "salesAmt": "6664500", "salesShare": "0.6", "salesInten": "-78740000", "salesChange": "-92.2", "salesAcc": "1377656000", "audiCnt": "1028", "audiInten": "-12046", "audiChange": "-92.1", "audiAcc": "209006", "scrnCnt": "83", "showCnt": "122"}, {"rnum": "10", "rank": "10", "rankInten": "1", "rankOldAndNew": "OLD", "movieCd": "20090188", "movieNm": "소명", "openDt": "2009-04-02", "salesAmt": "4969000", "salesShare": "0.4", "salesInten": "-1164500", "salesChange": "-19", "salesAcc": "318926000", "audiCnt": "935", "audiInten": "70", "audiChange": "8.1", "audiAcc": "50149", "scrnCnt": "20", "showCnt": "42"}]}}