{"boxOfficeResult": {"boxofficeType": "일별 박스오피스", "showRange": "20080729~20080729", "dailyBoxOfficeList": [{"rnum": "1", "rank": "1", "rankInten": "0", "rankOldAndNew": "OLD", "movieCd": "20072152", "movieNm": "좋은 놈, 나쁜 놈, 이상한 놈 ", "openDt": "2008-07-17", "salesAmt": "998393500", "salesShare": "39.5", "salesInten": "-91696000", "salesChange": "-8.4", "salesAcc": "28650161000", "audiCnt": "155553", "audiInten": "-13347", "audiChange": "-7.9", "audiAcc": "4366338", "scrnCnt": "655", "showCnt": "3180"}, {"rnum": "2", "rank": "2", "rankInten": "0", "rankOldAndNew": "OLD", "movieCd": "20080764", "movieNm": "님은 먼 곳에", "openDt": "2008-07-24", "salesAmt": "541613000", "salesShare": "21.5", "salesInten": "-102834000", "salesChange": "-16", "salesAcc": "6751721500", "audiCnt": "84443", "audiInten": "-15334", "audiChange": "-15.4", "audiAcc": "1026681", "scrnCnt": "475", "showCnt": "2536"}, {"rnum": "3", "rank": "3", "rankInten": "12", "rankOldAndNew": "OLD", "movieCd": "20080968", "movieNm": "눈에는 눈 이에는 이", "openDt": "2008-07-31", "salesAmt": "314131000", "salesShare": "12.4", "salesInten": "312677000", "salesChange": "21504.6", "salesAcc": "351347000", "audiCnt": "47379", "audiInten": "47037", "audiChange": "13753.5", "audiAcc": "55692", "scrnCnt": "290", "showCnt": "901"}, {"rnum": "4", "rank": "4", "rankInten": "-1", "rankOldAndNew": "OLD", "movieCd": "20080946", "movieNm": "님스 아일랜드", "openDt": "2008-07-17", "salesAmt": "145554000", "salesShare": "5.8", "salesInten": "5393000", "salesChange": "3.8", "salesAcc": "3376023000", "audiCnt": "24942", "audiInten": "1607", "audiChange": "6.9", "audiAcc": "544790", "scrnCnt": "224", "showCnt": "995"}, {"rnum": "5", "rank": "5", "rankInten": "-1", "rankOldAndNew": "OLD", "movieCd": "20080914", "movieNm": "적벽대전:거대한 전쟁의 시작", "openDt": "2008-07-10", "salesAmt": "113318000", "salesShare": "4.5", "salesInten": "-27835500", "salesChange": "-19.7", "salesAcc": "9884663000", "audiCnt": "17943", "audiInten": "-4029", "audiChange": "-18.3", "audiAcc": "1523019", "scrnCnt": "236", "showCnt": "777"}, {"rnum": "6", "rank": "6", "rankInten": "-1", "rankOldAndNew": "OLD", "movieCd": "20080962", "movieNm": "극장판 도라에몽:진구의 마계대모험 7인의 마법사", "openDt": "2008-07-17", "salesAmt": "83590500", "salesShare": "3.3", "salesInten": "10433500", "salesChange": "14.3", "salesAcc": "1087867000", "audiCnt": "14391", "audiInten": "2064", "audiChange": "16.7", "audiAcc": "179902", "scrnCnt": "74", "showCnt": "243"}, {"rnum": "7", "rank": "7", "rankInten": "0", "rankOldAndNew": "OLD", "movieCd": "20080963", "movieNm": "스페이스 침스:우주선을 찾아서", "openDt": "2008-07-17", "salesAmt": "72364000", "salesShare": "2.9", "salesInten": "14580000", "salesChange": "25.2", "salesAcc": "1131971000", "audiCnt": "12916", "audiInten": "2819", "audiChange": "27.9", "audiAcc": "193089", "scrnCnt": "160", "showCnt": "391"}, {"rnum": "8", "rank": "8", "rankInten": "-2", "rankOldAndNew": "OLD", "movieCd": "20080736", "movieNm": "강철중: 공공의 적 1-1", "openDt": "2008-06-19", "salesAmt": "51521500", "salesShare": "2.0", "salesInten": "-17482500", "salesChange": "-25.3", "salesAcc": "28568266600", "audiCnt": "7988", "audiInten": "-2529", "audiChange": "-24", "audiAcc": "4302304", "scrnCnt": "150", "showCnt": "396"}, {"rnum": "9", "rank": "9", "rankInten": "-1", "rankOldAndNew": "OLD", "movieCd": "20080873", "movieNm": "핸콕", "openDt": "2008-07-02", "salesAmt": "42800000", "salesShare": "1.7", "salesInten": "-9358000", "salesChange": "-17.9", "salesAcc": "17818823000", "audiCnt": "6774", "audiInten": "-1397", "audiChange": "-17.1", "audiAcc": "2718718", "scrnCnt": "161", "showCnt": "424"}, {"rnum": "10", "rank": "10", "rankInten": "-1", "rankOldAndNew": "OLD", "movieCd": "20080992", "movieNm": "100 피트", "openDt": "2008-07-24", "salesAmt": "38815500", "salesShare": "1.5", "salesInten": "-12860500", "salesChange": "-24.9", "salesAcc": "434646000", "audiCnt": "6050", "audiInten": "-1955", "audiChange": "-24.4", "audiAcc": "66010", "scrnCnt": "124", "showCnt": "455"}]}}