{"boxOfficeResult": {"boxofficeType": "일별 박스오피스", "showRange": "20230324~20230324", "dailyBoxOfficeList": [{"rnum": "1", "rank": "1", "rankInten": "0", "rankOldAndNew": "OLD", "movieCd": "20226270", "movieNm": "스즈메의 문단속", "openDt": "2023-03-08", "salesAmt": "1124940341", "salesShare": "61.3", "salesInten": "449763915", "salesChange": "66.6", "salesAcc": "24343845123", "audiCnt": "104883", "audiInten": "38894", "audiChange": "58.9", "audiAcc": "2312239", "scrnCnt": "1315", "showCnt": "5190"}, {"rnum": "2", "rank": "2", "rankInten": "0", "rankOldAndNew": "OLD", "movieCd": "20210544", "movieNm": "웅남이", "openDt": "2023-03-22", "salesAmt": "232541530", "salesShare": "12.7", "salesInten": "29054716", "salesChange": "14.3", "salesAcc": "694493208", "audiCnt": "25123", "audiInten": "1879", "audiChange": "8.1", "audiAcc": "79904", "scrnCnt": "771", "showCnt": "2978"}, {"rnum": "3", "rank": "3", "rankInten": "0", "rankOldAndNew": "OLD", "movieCd": "20228555", "movieNm": "더 퍼스트 슬램덩크", "openDt": "2023-01-04", "salesAmt": "137049070", "salesShare": "7.5", "salesInten": "45772208", "salesChange": "50.1", "salesAcc": "43318429500", "audiCnt": "12776", "audiInten": "3830", "audiChange": "42.8", "audiAcc": "4202992", "scrnCnt": "595", "showCnt": "1398"}, {"rnum": "4", "rank": "4", "rankInten": "0", "rankOldAndNew": "OLD", "movieCd": "20197654", "movieNm": "소울메이트", "openDt": "2023-03-15", "salesAmt": "70190731", "salesShare": "3.8", "salesInten": "14571330", "salesChange": "26.2", "salesAcc": "1498287143", "audiCnt": "6799", "audiInten": "780", "audiChange": "13", "audiAcc": "154650", "scrnCnt": "541", "showCnt": "1161"}, {"rnum": "5", "rank": "5", "rankInten": "0", "rankOldAndNew": "OLD", "movieCd": "20230767", "movieNm": "파벨만스", "openDt": "2023-03-22", "salesAmt": "45986678", "salesShare": "2.5", "salesInten": "9153227", "salesChange": "24.9", "salesAcc": "180749727", "audiCnt": "4498", "audiInten": "703", "audiChange": "18.5", "audiAcc": "17374", "scrnCnt": "408", "showCnt": "754"}, {"rnum": "6", "rank": "6", "rankInten": "1", "rankOldAndNew": "OLD", "movieCd": "20230340", "movieNm": "에브리씽 에브리웨어 올 앳 원스+", "openDt": "2023-03-01", "salesAmt": "34464872", "salesShare": "1.9", "salesInten": "9551189", "salesChange": "38.3", "salesAcc": "801844669", "audiCnt": "3309", "audiInten": "824", "audiChange": "33.2", "audiAcc": "77531", "scrnCnt": "219", "showCnt": "384"}, {"rnum": "7", "rank": "7", "rankInten": "1", "rankOldAndNew": "OLD", "movieCd": "20230533", "movieNm": "귀멸의 칼날: 상현집결, 그리고 도공 마을로", "openDt": "2023-03-02", "salesAmt": "38870800", "salesShare": "2.1", "salesInten": "10675500", "salesChange": "37.9", "salesAcc": "6282557300", "audiCnt": "2980", "audiInten": "724", "audiChange": "32.1", "audiAcc": "510487", "scrnCnt": "174", "showCnt": "394"}, {"rnum": "8", "rank": "8", "rankInten": "-2", "rankOldAndNew": "OLD", "movieCd": "20224780", "movieNm": "모나리자와 블러드 문", "openDt": "2023-03-22", "salesAmt": "21233692", "salesShare": "1.2", "salesInten": "-3143783", "salesChange": "-12.9", "salesAcc": "100783943", "audiCnt": "2191", "audiInten": "-723", "audiChange": "-24.8", "audiAcc": "11186", "scrnCnt": "318", "showCnt": "519"}, {"rnum": "9", "rank": "9", "rankInten": "4", "rankOldAndNew": "OLD", "movieCd": "20230081", "movieNm": "샤잠! 신들의 분노", "openDt": "2023-03-15", "salesAmt": "11988185", "salesShare": "0.7", "salesInten": "3512689", "salesChange": "41.4", "salesAcc": "769832057", "audiCnt": "1164", "audiInten": "310", "audiChange": "36.3", "audiAcc": "72691", "scrnCnt": "250", "showCnt": "336"}, {"rnum": "10", "rank": "10", "rankInten": "0", "rankOldAndNew": "OLD", "movieCd": "20230495", "movieNm": "아임 히어로 더 파이널", "openDt": "2023-03-01", "salesAmt": "27048000", "salesShare": "1.5", "salesInten": "-39000", "salesChange": "-0.1", "salesAcc": "5311157500", "audiCnt": "1127", "audiInten": "-2", "audiChange": "-0.2", "audiAcc": "219656", "scrnCnt": "47", "showCnt": "118"}]}}