{"boxOfficeResult": {"boxofficeType": "일별 박스오피스", "showRange": "20070619~20070619", "dailyBoxOfficeList": [{"rnum": "1", "rank": "1", "rankInten": "0", "rankOldAndNew": "OLD", "movieCd": "20070058", "movieNm": "오션스 써틴", "openDt": "2007-06-14", "salesAmt": "321462000", "salesShare": "33.4", "salesInten": "-11246000", "salesChange": "-3.4", "salesAcc": "3863530000", "audiCnt": "48790", "audiInten": "-1791", "audiChange": "-3.5", "audiAcc": "584010", "scrnCnt": "222", "showCnt": "1349"}, {"rnum": "2", "rank": "2", "rankInten": "0", "rankOldAndNew": "OLD", "movieCd": "20070116", "movieNm": "슈렉3", "openDt": "2007-06-06", "salesAmt": "162611500", "salesShare": "16.9", "salesInten": "-2283500", "salesChange": "-1.4", "salesAcc": "14317420500", "audiCnt": "25553", "audiInten": "108", "audiChange": "0.4", "audiAcc": "2256139", "scrnCnt": "384", "showCnt": "2095"}, {"rnum": "3", "rank": "3", "rankInten": "0", "rankOldAndNew": "OLD", "movieCd": "20070128", "movieNm": "황진이", "openDt": "2007-06-06", "salesAmt": "130915000", "salesShare": "13.6", "salesInten": "-3220500", "salesChange": "-2.4", "salesAcc": "6720528000", "audiCnt": "21106", "audiInten": "-325", "audiChange": "-1.5", "audiAcc": "1027940", "scrnCnt": "351", "showCnt": "1531"}, {"rnum": "4", "rank": "4", "rankInten": "2", "rankOldAndNew": "OLD", "movieCd": "20070196", "movieNm": "러브 & 트러블", "openDt": "2007-06-14", "salesAmt": "99300500", "salesShare": "10.3", "salesInten": "9674500", "salesChange": "10.8", "salesAcc": "938371000", "audiCnt": "15279", "audiInten": "1487", "audiChange": "10.8", "audiAcc": "139668", "scrnCnt": "165", "showCnt": "1121"}, {"rnum": "5", "rank": "5", "rankInten": "0", "rankOldAndNew": "OLD", "movieCd": "20070115", "movieNm": "밀양", "openDt": "2007-05-23", "salesAmt": "85821500", "salesShare": "8.9", "salesInten": "-2336000", "salesChange": "-2.6", "salesAcc": "9451496500", "audiCnt": "14360", "audiInten": "-284", "audiChange": "-1.9", "audiAcc": "1473422", "scrnCnt": "214", "showCnt": "946"}, {"rnum": "6", "rank": "6", "rankInten": "-2", "rankOldAndNew": "OLD", "movieCd": "20070057", "movieNm": "캐리비안의 해적: 세상의 끝에서", "openDt": "2007-05-23", "salesAmt": "89887000", "salesShare": "9.3", "salesInten": "-6508500", "salesChange": "-6.8", "salesAcc": "27814693000", "audiCnt": "14178", "audiInten": "-915", "audiChange": "-6.1", "audiAcc": "4365487", "scrnCnt": "276", "showCnt": "1039"}, {"rnum": "7", "rank": "7", "rankInten": "0", "rankOldAndNew": "OLD", "movieCd": "20070092", "movieNm": "메신져 - 죽은자들의 경고", "openDt": "2007-06-06", "salesAmt": "31291500", "salesShare": "3.3", "salesInten": "-3248000", "salesChange": "-9.4", "salesAcc": "1512634000", "audiCnt": "4801", "audiInten": "-516", "audiChange": "-9.7", "audiAcc": "235470", "scrnCnt": "127", "showCnt": "521"}, {"rnum": "8", "rank": "8", "rankInten": "0", "rankOldAndNew": "OLD", "movieCd": "20070216", "movieNm": "시간을 달리는 소녀", "openDt": "2007-06-14", "salesAmt": "11516500", "salesShare": "1.2", "salesInten": "-524500", "salesChange": "-4.4", "salesAcc": "100695500", "audiCnt": "1895", "audiInten": "-32", "audiChange": "-1.7", "audiAcc": "16138", "scrnCnt": "6", "showCnt": "40"}, {"rnum": "9", "rank": "9", "rankInten": "0", "rankOldAndNew": "OLD", "movieCd": "20070179", "movieNm": "황색 눈물", "openDt": "2007-06-14", "salesAmt": "10484000", "salesShare": "1.1", "salesInten": "292500", "salesChange": "2.9", "salesAcc": "130676000", "audiCnt": "1645", "audiInten": "44", "audiChange": "2.7", "audiAcc": "20200", "scrnCnt": "14", "showCnt": "78"}, {"rnum": "10", "rank": "10", "rankInten": "32", "rankOldAndNew": "OLD", "movieCd": "20070003", "movieNm": "2007 [통합]영화제/기획전/회고전 등", "openDt": " ", "salesAmt": "2102600", "salesShare": "0.2", "salesInten": "2090600", "salesChange": "17421.7", "salesAcc": "222929800", "audiCnt": "374", "audiInten": "371", "audiChange": "12366.7", "audiAcc": "38912", "scrnCnt": "3", "showCnt": "6"}]}}