{"boxOfficeResult": {"boxofficeType": "일별 박스오피스", "showRange": "20050112~20050112", "dailyBoxOfficeList": [{"rnum": "1", "rank": "1", "rankInten": "0", "rankOldAndNew": "OLD", "movieCd": "20048103", "movieNm": "오션스 트웰브", "openDt": "2005-01-07", "salesAmt": "264930000", "salesShare": "20.2", "salesInten": "-12781000", "salesChange": "-4.6", "salesAcc": "2979994000", "audiCnt": "41404", "audiInten": "-2042", "audiChange": "-4.7", "audiAcc": "461644", "scrnCnt": "149", "showCnt": "865"}, {"rnum": "2", "rank": "2", "rankInten": "0", "rankOldAndNew": "OLD", "movieCd": "20040756", "movieNm": "하울의 움직이는 성", "openDt": "2004-12-23", "salesAmt": "246726500", "salesShare": "18.8", "salesInten": "-287500", "salesChange": "-0.1", "salesAcc": "11503800000", "audiCnt": "40070", "audiInten": "-93", "audiChange": "-0.2", "audiAcc": "1841903", "scrnCnt": "159", "showCnt": "906"}, {"rnum": "3", "rank": "3", "rankInten": "0", "rankOldAndNew": "OLD", "movieCd": "20040744", "movieNm": "샤크", "openDt": "2005-01-07", "salesAmt": "227050000", "salesShare": "17.3", "salesInten": "-11403500", "salesChange": "-4.8", "salesAcc": "2827569000", "audiCnt": "36922", "audiInten": "-1848", "audiChange": "-4.8", "audiAcc": "451107", "scrnCnt": "172", "showCnt": "1150"}, {"rnum": "4", "rank": "4", "rankInten": "0", "rankOldAndNew": "OLD", "movieCd": "20040755", "movieNm": "내셔널 트레져", "openDt": "2004-12-31", "salesAmt": "202771500", "salesShare": "15.4", "salesInten": "-9188000", "salesChange": "-4.3", "salesAcc": "5666698500", "audiCnt": "31771", "audiInten": "-1370", "audiChange": "-4.1", "audiAcc": "881572", "scrnCnt": "131", "showCnt": "737"}, {"rnum": "5", "rank": "5", "rankInten": "0", "rankOldAndNew": "OLD", "movieCd": "20040706", "movieNm": "알렉산더", "openDt": "2004-12-31", "salesAmt": "167494500", "salesShare": "12.7", "salesInten": "-13883500", "salesChange": "-7.7", "salesAcc": "7405281289", "audiCnt": "26373", "audiInten": "-2070", "audiChange": "-7.3", "audiAcc": "1163414", "scrnCnt": "183", "showCnt": "791"}, {"rnum": "6", "rank": "6", "rankInten": "0", "rankOldAndNew": "OLD", "movieCd": "20040745", "movieNm": "인크레더블", "openDt": "2004-12-15", "salesAmt": "56845000", "salesShare": "4.3", "salesInten": "261000", "salesChange": "0.5", "salesAcc": "5269000000", "audiCnt": "9151", "audiInten": "22", "audiChange": "0.2", "audiAcc": "843690", "scrnCnt": "85", "showCnt": "336"}, {"rnum": "7", "rank": "7", "rankInten": "0", "rankOldAndNew": "OLD", "movieCd": "20040750", "movieNm": "신석기 블루스", "openDt": "2004-12-30", "salesAmt": "49126000", "salesShare": "3.7", "salesInten": "-4242000", "salesChange": "-7.9", "salesAcc": "1793497000", "audiCnt": "7827", "audiInten": "-653", "audiChange": "-7.7", "audiAcc": "281850", "scrnCnt": "90", "showCnt": "464"}, {"rnum": "8", "rank": "8", "rankInten": "0", "rankOldAndNew": "OLD", "movieCd": "20040721", "movieNm": "오페라의 유령", "openDt": "2004-12-08", "salesAmt": "37778000", "salesShare": "2.9", "salesInten": "3880500", "salesChange": "11.4", "salesAcc": "9777631000", "audiCnt": "5747", "audiInten": "491", "audiChange": "9.3", "audiAcc": "1534723", "scrnCnt": "55", "showCnt": "157"}, {"rnum": "9", "rank": "9", "rankInten": "0", "rankOldAndNew": "OLD", "movieCd": "20040743", "movieNm": "브리짓 존스의 일기2 : 열정과 애정", "openDt": "2004-12-08", "salesAmt": "17864500", "salesShare": "1.4", "salesInten": "930500", "salesChange": "5.5", "salesAcc": "7254155000", "audiCnt": "2688", "audiInten": "144", "audiChange": "5.7", "audiAcc": "1117043", "scrnCnt": "32", "showCnt": "118"}, {"rnum": "10", "rank": "10", "rankInten": "0", "rankOldAndNew": "NEW", "movieCd": "20040774", "movieNm": "몽정기2", "openDt": "2005-01-14", "salesAmt": "16841500", "salesShare": "1.3", "salesInten": "16841500", "salesChange": "100", "salesAcc": "24767000", "audiCnt": "2683", "audiInten": "2683", "audiChange": "100", "audiAcc": "4124", "scrnCnt": "10", "showCnt": "13"}]}}