{"boxOfficeResult": {"boxofficeType": "일별 박스오피스", "showRange": "20100709~20100709", "dailyBoxOfficeList": [{"rnum": "1", "rank": "1", "rankInten": "0", "rankOldAndNew": "OLD", "movieCd": "20100361", "movieNm": "이클립스", "openDt": "2010-07-07", "salesAmt": "1087456000", "salesShare": "36.2", "salesInten": "115465000", "salesChange": "11.9", "salesAcc": "3301235500", "audiCnt": "144986", "audiInten": "9660", "audiChange": "7.1", "audiAcc": "452806", "scrnCnt": "497", "showCnt": "2852"}, {"rnum": "2", "rank": "2", "rankInten": "0", "rankOldAndNew": "OLD", "movieCd": "20100310", "movieNm": "나잇&데이", "openDt": "2010-06-24", "salesAmt": "412465000", "salesShare": "13.7", "salesInten": "114632000", "salesChange": "38.5", "salesAcc": "11970915100", "audiCnt": "54437", "audiInten": "12992", "audiChange": "31.3", "audiAcc": "1592719", "scrnCnt": "300", "showCnt": "1597"}, {"rnum": "3", "rank": "3", "rankInten": "0", "rankOldAndNew": "OLD", "movieCd": "20100333", "movieNm": "슈렉 포에버", "openDt": "2010-07-01", "salesAmt": "585183500", "salesShare": "19.5", "salesInten": "176003000", "salesChange": "43", "salesAcc": "10452261600", "audiCnt": "53473", "audiInten": "15328", "audiChange": "40.2", "audiAcc": "997264", "scrnCnt": "423", "showCnt": "2170"}, {"rnum": "4", "rank": "4", "rankInten": "0", "rankOldAndNew": "OLD", "movieCd": "20100353", "movieNm": "파괴된 사나이", "openDt": "2010-07-01", "salesAmt": "350714500", "salesShare": "11.7", "salesInten": "77481500", "salesChange": "28.4", "salesAcc": "4957221100", "audiCnt": "45494", "audiInten": "7892", "audiChange": "21", "audiAcc": "655205", "scrnCnt": "312", "showCnt": "1748"}, {"rnum": "5", "rank": "5", "rankInten": "0", "rankOldAndNew": "OLD", "movieCd": "20100296", "movieNm": "포화속으로", "openDt": "2010-06-16", "salesAmt": "312617500", "salesShare": "10.4", "salesInten": "65863500", "salesChange": "26.7", "salesAcc": "19243230600", "audiCnt": "45002", "audiInten": "8738", "audiChange": "24.1", "audiAcc": "2657662", "scrnCnt": "345", "showCnt": "1664"}, {"rnum": "6", "rank": "6", "rankInten": "0", "rankOldAndNew": "OLD", "movieCd": "20090927", "movieNm": "방자전", "openDt": "2010-06-02", "salesAmt": "75613000", "salesShare": "2.5", "salesInten": "20487000", "salesChange": "37.2", "salesAcc": "21962463500", "audiCnt": "9919", "audiInten": "2191", "audiChange": "28.4", "audiAcc": "2914758", "scrnCnt": "142", "showCnt": "383"}, {"rnum": "7", "rank": "7", "rankInten": "0", "rankOldAndNew": "OLD", "movieCd": "20100362", "movieNm": "킬러 인사이드 미", "openDt": "2010-07-07", "salesAmt": "50940500", "salesShare": "1.7", "salesInten": "9429000", "salesChange": "22.7", "salesAcc": "132861500", "audiCnt": "6620", "audiInten": "894", "audiChange": "15.6", "audiAcc": "17938", "scrnCnt": "120", "showCnt": "716"}, {"rnum": "8", "rank": "8", "rankInten": "0", "rankOldAndNew": "OLD", "movieCd": "20090943", "movieNm": "스플라이스", "openDt": "2010-07-01", "salesAmt": "45640500", "salesShare": "1.5", "salesInten": "12609000", "salesChange": "38.2", "salesAcc": "1014018000", "audiCnt": "5703", "audiInten": "1285", "audiChange": "29.1", "audiAcc": "131065", "scrnCnt": "117", "showCnt": "365"}, {"rnum": "9", "rank": "9", "rankInten": "0", "rankOldAndNew": "OLD", "movieCd": "20100210", "movieNm": "맨발의 꿈", "openDt": "2010-06-24", "salesAmt": "25855000", "salesShare": "0.9", "salesInten": "6627500", "salesChange": "34.5", "salesAcc": "2096090000", "audiCnt": "3462", "audiInten": "687", "audiChange": "24.8", "audiAcc": "291689", "scrnCnt": "78", "showCnt": "167"}, {"rnum": "10", "rank": "10", "rankInten": "0", "rankOldAndNew": "OLD", "movieCd": "20100339", "movieNm": "필립모리스", "openDt": "2010-07-01", "salesAmt": "17037000", "salesShare": "0.6", "salesInten": "4937500", "salesChange": "40.8", "salesAcc": "571270200", "audiCnt": "2123", "audiInten": "498", "audiChange": "30.6", "audiAcc": "74684", "scrnCnt": "64", "showCnt": "143"}]}}