{"boxOfficeResult": {"boxofficeType": "일별 박스오피스", "showRange": "20041008~20041008", "dailyBoxOfficeList": [{"rnum": "1", "rank": "1", "rankInten": "12", "rankOldAndNew": "OLD", "movieCd": "20040628", "movieNm": "우리 형", "openDt": "2004-10-08", "salesAmt": "712081000", "salesShare": "56.0", "salesInten": "708676000", "salesChange": "20812.8", "salesAcc": "717986000", "audiCnt": "116069", "audiInten": "115315", "audiChange": "15293.8", "audiAcc": "117323", "scrnCnt": "179", "showCnt": "1113"}, {"rnum": "2", "rank": "2", "rankInten": "1", "rankOldAndNew": "OLD", "movieCd": "20040656", "movieNm": "세상의 중심에서 사랑을 외치다", "openDt": "2004-10-08", "salesAmt": "165164000", "salesShare": "13.0", "salesInten": "105007000", "salesChange": "174.6", "salesAcc": "228321000", "audiCnt": "25722", "audiInten": "15684", "audiChange": "156.2", "audiAcc": "36292", "scrnCnt": "96", "showCnt": "526"}, {"rnum": "3", "rank": "3", "rankInten": "-2", "rankOldAndNew": "OLD", "movieCd": "20040649", "movieNm": "귀신이 산다", "openDt": "2004-09-17", "salesAmt": "107708500", "salesShare": "8.5", "salesInten": "-13489500", "salesChange": "-11.1", "salesAcc": "10569127000", "audiCnt": "17517", "audiInten": "-2207", "audiChange": "-11.2", "audiAcc": "1662960", "scrnCnt": "109", "showCnt": "601"}, {"rnum": "4", "rank": "4", "rankInten": "0", "rankOldAndNew": "OLD", "movieCd": "20040676", "movieNm": "스텝포드 와이프", "openDt": "2004-10-01", "salesAmt": "55216000", "salesShare": "4.3", "salesInten": "-8052500", "salesChange": "-12.7", "salesAcc": "669404000", "audiCnt": "8362", "audiInten": "-1664", "audiChange": "-16.6", "audiAcc": "101564", "scrnCnt": "35", "showCnt": "237"}, {"rnum": "5", "rank": "5", "rankInten": "-3", "rankOldAndNew": "OLD", "movieCd": "20040554", "movieNm": "가족", "openDt": "2004-09-03", "salesAmt": "43033000", "salesShare": "3.4", "salesInten": "-25153000", "salesChange": "-36.9", "salesAcc": "7603342000", "audiCnt": "7093", "audiInten": "-4034", "audiChange": "-36.3", "audiAcc": "1199072", "scrnCnt": "72", "showCnt": "407"}, {"rnum": "6", "rank": "6", "rankInten": "2", "rankOldAndNew": "OLD", "movieCd": "20040670", "movieNm": "맨 온 파이어", "openDt": "2004-09-24", "salesAmt": "40353000", "salesShare": "3.2", "salesInten": "-6899000", "salesChange": "-14.6", "salesAcc": "1514628000", "audiCnt": "6311", "audiInten": "-1306", "audiChange": "-17.1", "audiAcc": "234359", "scrnCnt": "51", "showCnt": "243"}, {"rnum": "7", "rank": "7", "rankInten": "-2", "rankOldAndNew": "OLD", "movieCd": "20040651", "movieNm": "꽃피는 봄이 오면", "openDt": "2004-09-23", "salesAmt": "35729500", "salesShare": "2.8", "salesInten": "-21747000", "salesChange": "-37.8", "salesAcc": "2957201500", "audiCnt": "5951", "audiInten": "-3218", "audiChange": "-35.1", "audiAcc": "457973", "scrnCnt": "78", "showCnt": "337"}, {"rnum": "8", "rank": "8", "rankInten": "-1", "rankOldAndNew": "OLD", "movieCd": "20040650", "movieNm": "빌리지", "openDt": "2004-09-24", "salesAmt": "27963000", "salesShare": "2.2", "salesInten": "-22903000", "salesChange": "-45", "salesAcc": "2309309000", "audiCnt": "4275", "audiInten": "-3803", "audiChange": "-47.1", "audiAcc": "348894", "scrnCnt": "56", "showCnt": "247"}, {"rnum": "9", "rank": "9", "rankInten": "-3", "rankOldAndNew": "OLD", "movieCd": "20040619", "movieNm": "슈퍼스타 감사용", "openDt": "2004-09-17", "salesAmt": "24582500", "salesShare": "1.9", "salesInten": "-27722500", "salesChange": "-53", "salesAcc": "3876737500", "audiCnt": "3845", "audiInten": "-4413", "audiChange": "-53.4", "audiAcc": "595907", "scrnCnt": "57", "showCnt": "247"}, {"rnum": "10", "rank": "10", "rankInten": "5", "rankOldAndNew": "OLD", "movieCd": "20040686", "movieNm": "이노센스", "openDt": "2004-10-08", "salesAmt": "22266500", "salesShare": "1.8", "salesInten": "18347500", "salesChange": "468.2", "salesAcc": "26185500", "audiCnt": "3368", "audiInten": "2736", "audiChange": "432.9", "audiAcc": "4000", "scrnCnt": "54", "showCnt": "286"}]}}