{"boxOfficeResult": {"boxofficeType": "일별 박스오피스", "showRange": "20090115~20090115", "dailyBoxOfficeList": [{"rnum": "1", "rank": "1", "rankInten": "0", "rankOldAndNew": "OLD", "movieCd": "20081716", "movieNm": "쌍화점", "openDt": "2008-12-30", "salesAmt": "451350000", "salesShare": "28.5", "salesInten": "-26589000", "salesChange": "-5.6", "salesAcc": "18411531500", "audiCnt": "69792", "audiInten": "-3898", "audiChange": "-5.3", "audiAcc": "2722340", "scrnCnt": "448", "showCnt": "2230"}, {"rnum": "2", "rank": "2", "rankInten": "0", "rankOldAndNew": "OLD", "movieCd": "20081672", "movieNm": "과속스캔들", "openDt": "2008-12-03", "salesAmt": "360157000", "salesShare": "22.8", "salesInten": "23667000", "salesChange": "7", "salesAcc": "39514957500", "audiCnt": "56601", "audiInten": "3790", "audiChange": "7.2", "audiAcc": "6022662", "scrnCnt": "328", "showCnt": "1909"}, {"rnum": "3", "rank": "3", "rankInten": "0", "rankOldAndNew": "OLD", "movieCd": "20081809", "movieNm": "트랜스포터-라스트 미션", "openDt": "2009-01-08", "salesAmt": "211096500", "salesShare": "13.3", "salesInten": "-21725000", "salesChange": "-9.3", "salesAcc": "3680422000", "audiCnt": "32661", "audiInten": "-3225", "audiChange": "-9", "audiAcc": "557987", "scrnCnt": "252", "showCnt": "1645"}, {"rnum": "4", "rank": "4", "rankInten": "0", "rankOldAndNew": "OLD", "movieCd": "20081791", "movieNm": "마다가스카 2", "openDt": "2009-01-08", "salesAmt": "172983500", "salesShare": "10.9", "salesInten": "-15575000", "salesChange": "-8.3", "salesAcc": "3475776500", "audiCnt": "29477", "audiInten": "-2492", "audiChange": "-7.8", "audiAcc": "568333", "scrnCnt": "336", "showCnt": "1644"}, {"rnum": "5", "rank": "5", "rankInten": "0", "rankOldAndNew": "OLD", "movieCd": "20081703", "movieNm": "예스맨", "openDt": "2008-12-17", "salesAmt": "89130500", "salesShare": "5.6", "salesInten": "1691500", "salesChange": "1.9", "salesAcc": "8424303500", "audiCnt": "13718", "audiInten": "295", "audiChange": "2.2", "audiAcc": "1267946", "scrnCnt": "194", "showCnt": "653"}, {"rnum": "6", "rank": "6", "rankInten": "0", "rankOldAndNew": "NEW", "movieCd": "20090015", "movieNm": "적벽대전 2 : 최후의 결전", "openDt": "2009-01-22", "salesAmt": "46352000", "salesShare": "2.9", "salesInten": "46352000", "salesChange": "100", "salesAcc": "49761000", "audiCnt": "11588", "audiInten": "11588", "audiChange": "100", "audiAcc": "12075", "scrnCnt": "16", "showCnt": "58"}, {"rnum": "7", "rank": "7", "rankInten": "-1", "rankOldAndNew": "OLD", "movieCd": "20081790", "movieNm": "디파이언스", "openDt": "2009-01-08", "salesAmt": "66762000", "salesShare": "4.2", "salesInten": "-376000", "salesChange": "-0.6", "salesAcc": "881749000", "audiCnt": "10349", "audiInten": "-94", "audiChange": "-0.9", "audiAcc": "133449", "scrnCnt": "154", "showCnt": "609"}, {"rnum": "8", "rank": "8", "rankInten": "-1", "rankOldAndNew": "OLD", "movieCd": "20081744", "movieNm": "볼트", "openDt": "2008-12-31", "salesAmt": "45847500", "salesShare": "2.9", "salesInten": "-10835000", "salesChange": "-19.1", "salesAcc": "4368750500", "audiCnt": "7644", "audiInten": "-1480", "audiChange": "-16.2", "audiAcc": "658669", "scrnCnt": "237", "showCnt": "669"}, {"rnum": "9", "rank": "9", "rankInten": "-1", "rankOldAndNew": "OLD", "movieCd": "20081686", "movieNm": "벼랑 위의 포뇨", "openDt": "2008-12-17", "salesAmt": "20916500", "salesShare": "1.3", "salesInten": "-5221500", "salesChange": "-20", "salesAcc": "9203770500", "audiCnt": "3600", "audiInten": "-907", "audiChange": "-20.1", "audiAcc": "1465408", "scrnCnt": "146", "showCnt": "345"}, {"rnum": "10", "rank": "10", "rankInten": "-1", "rankOldAndNew": "OLD", "movieCd": "20081696", "movieNm": "잃어버린 세계를 찾아서", "openDt": "2008-12-17", "salesAmt": "21670500", "salesShare": "1.4", "salesInten": "-2190000", "salesChange": "-9.2", "salesAcc": "9024800500", "audiCnt": "3478", "audiInten": "-376", "audiChange": "-9.8", "audiAcc": "1393441", "scrnCnt": "171", "showCnt": "393"}]}}