{"boxOfficeResult": {"boxofficeType": "일별 박스오피스", "showRange": "20110308~20110308", "dailyBoxOfficeList": [{"rnum": "1", "rank": "1", "rankInten": "0", "rankOldAndNew": "OLD", "movieCd": "20119577", "movieNm": "블랙 스완", "openDt": "2011-02-24", "salesAmt": "280945000", "salesShare": "28.3", "salesInten": "8516500", "salesChange": "3.1", "salesAcc": "7593126000", "audiCnt": "38774", "audiInten": "1330", "audiChange": "3.6", "audiAcc": "984569", "scrnCnt": "313", "showCnt": "1479"}, {"rnum": "2", "rank": "2", "rankInten": "0", "rankOldAndNew": "OLD", "movieCd": "20119337", "movieNm": "그대를 사랑합니다", "openDt": "2011-02-17", "salesAmt": "147195500", "salesShare": "14.9", "salesInten": "11403500", "salesChange": "8.4", "salesAcc": "4936829000", "audiCnt": "20938", "audiInten": "1610", "audiChange": "8.3", "audiAcc": "668519", "scrnCnt": "282", "showCnt": "860"}, {"rnum": "3", "rank": "3", "rankInten": "0", "rankOldAndNew": "OLD", "movieCd": "20119430", "movieNm": "컨트롤러", "openDt": "2011-03-03", "salesAmt": "116472000", "salesShare": "11.8", "salesInten": "-10398500", "salesChange": "-8.2", "salesAcc": "2235600500", "audiCnt": "15844", "audiInten": "-1457", "audiChange": "-8.4", "audiAcc": "290763", "scrnCnt": "316", "showCnt": "1567"}, {"rnum": "4", "rank": "4", "rankInten": "0", "rankOldAndNew": "OLD", "movieCd": "20119341", "movieNm": "아이들...", "openDt": "2011-02-17", "salesAmt": "78761000", "salesShare": "7.9", "salesInten": "-13902500", "salesChange": "-15", "salesAcc": "13004052000", "audiCnt": "11224", "audiInten": "-2007", "audiChange": "-15.2", "audiAcc": "1786645", "scrnCnt": "295", "showCnt": "1228"}, {"rnum": "5", "rank": "5", "rankInten": "0", "rankOldAndNew": "OLD", "movieCd": "20119420", "movieNm": "아이 엠 넘버 포", "openDt": "2011-02-24", "salesAmt": "74770000", "salesShare": "7.5", "salesInten": "-611500", "salesChange": "-0.8", "salesAcc": "4621644500", "audiCnt": "9867", "audiInten": "-140", "audiChange": "-1.4", "audiAcc": "609448", "scrnCnt": "238", "showCnt": "1036"}, {"rnum": "6", "rank": "6", "rankInten": "0", "rankOldAndNew": "OLD", "movieCd": "20102414", "movieNm": "조선명탐정 : 각시투구꽃의 비밀", "openDt": "2011-01-27", "salesAmt": "66452500", "salesShare": "6.7", "salesInten": "-3853500", "salesChange": "-5.5", "salesAcc": "35393417500", "audiCnt": "9307", "audiInten": "-487", "audiChange": "-5", "audiAcc": "4724863", "scrnCnt": "254", "showCnt": "828"}, {"rnum": "7", "rank": "7", "rankInten": "0", "rankOldAndNew": "OLD", "movieCd": "20119630", "movieNm": "랭고", "openDt": "2011-03-03", "salesAmt": "49997000", "salesShare": "5.0", "salesInten": "-6962000", "salesChange": "-12.2", "salesAcc": "1504813000", "audiCnt": "6781", "audiInten": "-993", "audiChange": "-12.8", "audiAcc": "206282", "scrnCnt": "274", "showCnt": "926"}, {"rnum": "8", "rank": "8", "rankInten": "0", "rankOldAndNew": "OLD", "movieCd": "19820019", "movieNm": "만추", "openDt": "2011-02-17", "salesAmt": "26707500", "salesShare": "2.7", "salesInten": "463000", "salesChange": "1.8", "salesAcc": "6225371000", "audiCnt": "3820", "audiInten": "-29", "audiChange": "-0.8", "audiAcc": "833584", "scrnCnt": "173", "showCnt": "359"}, {"rnum": "9", "rank": "9", "rankInten": "0", "rankOldAndNew": "OLD", "movieCd": "20119507", "movieNm": "사랑한다, 사랑하지 않는다", "openDt": "2011-03-03", "salesAmt": "25404500", "salesShare": "2.6", "salesInten": "-825000", "salesChange": "-3.1", "salesAcc": "363936000", "audiCnt": "3523", "audiInten": "-83", "audiChange": "-2.3", "audiAcc": "47468", "scrnCnt": "71", "showCnt": "410"}, {"rnum": "10", "rank": "10", "rankInten": "0", "rankOldAndNew": "OLD", "movieCd": "20119429", "movieNm": "언노운", "openDt": "2011-02-17", "salesAmt": "23050500", "salesShare": "2.3", "salesInten": "-89000", "salesChange": "-0.4", "salesAcc": "3876840000", "audiCnt": "3153", "audiInten": "22", "audiChange": "0.7", "audiAcc": "512952", "scrnCnt": "127", "showCnt": "333"}]}}