{"boxOfficeResult": {"boxofficeType": "일별 박스오피스", "showRange": "20190208~20190208", "dailyBoxOfficeList": [{"rnum": "1", "rank": "1", "rankInten": "0", "rankOldAndNew": "OLD", "movieCd": "20182530", "movieNm": "극한직업", "openDt": "2019-01-23", "salesAmt": "3614329334", "salesShare": "61.7", "salesInten": "-91443976", "salesChange": "-2.5", "salesAcc": "98819370557", "audiCnt": "409794", "audiInten": "-50654", "audiChange": "-11", "audiAcc": "11402599", "scrnCnt": "1595", "showCnt": "8784"}, {"rnum": "2", "rank": "2", "rankInten": "0", "rankOldAndNew": "OLD", "movieCd": "20188282", "movieNm": "알리타: 배틀 엔젤", "openDt": "2019-02-05", "salesAmt": "1116482674", "salesShare": "19.1", "salesInten": "47890094", "salesChange": "4.5", "salesAcc": "7784691194", "audiCnt": "114672", "audiInten": "-4803", "audiChange": "-4", "audiAcc": "793540", "scrnCnt": "994", "showCnt": "4039"}, {"rnum": "3", "rank": "3", "rankInten": "0", "rankOldAndNew": "OLD", "movieCd": "20180868", "movieNm": "뺑반", "openDt": "2019-01-30", "salesAmt": "472598946", "salesShare": "8.1", "salesInten": "-23504894", "salesChange": "-4.7", "salesAcc": "13050479313", "audiCnt": "53774", "audiInten": "-8151", "audiChange": "-13.2", "audiAcc": "1570247", "scrnCnt": "734", "showCnt": "2344"}, {"rnum": "4", "rank": "4", "rankInten": "0", "rankOldAndNew": "OLD", "movieCd": "20186261", "movieNm": "드래곤 길들이기 3", "openDt": "2019-01-30", "salesAmt": "298065260", "salesShare": "5.1", "salesInten": "-285030", "salesChange": "-0.1", "salesAcc": "8511632186", "audiCnt": "35556", "audiInten": "-3044", "audiChange": "-7.9", "audiAcc": "1015699", "scrnCnt": "692", "showCnt": "1651"}, {"rnum": "5", "rank": "5", "rankInten": "0", "rankOldAndNew": "OLD", "movieCd": "20185478", "movieNm": "극장판 헬로카봇: 옴파로스 섬의 비밀", "openDt": "2019-01-31", "salesAmt": "56243330", "salesShare": "1.0", "salesInten": "-5660580", "salesChange": "-9.1", "salesAcc": "3581804480", "audiCnt": "7492", "audiInten": "-1099", "audiChange": "-12.8", "audiAcc": "456319", "scrnCnt": "393", "showCnt": "584"}, {"rnum": "6", "rank": "6", "rankInten": "0", "rankOldAndNew": "OLD", "movieCd": "20185444", "movieNm": "레고 무비2", "openDt": "2019-02-06", "salesAmt": "42776590", "salesShare": "0.7", "salesInten": "2880030", "salesChange": "7.2", "salesAcc": "291130570", "audiCnt": "5610", "audiInten": "-29", "audiChange": "-0.5", "audiAcc": "36823", "scrnCnt": "379", "showCnt": "538"}, {"rnum": "7", "rank": "7", "rankInten": "9", "rankOldAndNew": "OLD", "movieCd": "20174169", "movieNm": "기묘한 가족", "openDt": "2019-02-13", "salesAmt": "35159000", "salesShare": "0.6", "salesInten": "29199000", "salesChange": "489.9", "salesAcc": "97521000", "audiCnt": "5271", "audiInten": "4526", "audiChange": "607.5", "audiAcc": "13136", "scrnCnt": "19", "showCnt": "22"}, {"rnum": "8", "rank": "8", "rankInten": "0", "rankOldAndNew": "OLD", "movieCd": "20184105", "movieNm": "말모이", "openDt": "2019-01-09", "salesAmt": "32978800", "salesShare": "0.6", "salesInten": "6021900", "salesChange": "22.3", "salesAcc": "23756733980", "audiCnt": "3895", "audiInten": "476", "audiChange": "13.9", "audiAcc": "2836628", "scrnCnt": "151", "showCnt": "260"}, {"rnum": "9", "rank": "9", "rankInten": "-2", "rankOldAndNew": "OLD", "movieCd": "20185124", "movieNm": "러브 유어셀프 인 서울", "openDt": "2019-01-26", "salesAmt": "36151000", "salesShare": "0.6", "salesInten": "1431000", "salesChange": "4.1", "salesAcc": "3014534400", "audiCnt": "3641", "audiInten": "121", "audiChange": "3.4", "audiAcc": "322932", "scrnCnt": "48", "showCnt": "70"}, {"rnum": "10", "rank": "10", "rankInten": "-1", "rankOldAndNew": "OLD", "movieCd": "20184896", "movieNm": "가버나움", "openDt": "2019-01-24", "salesAmt": "26269330", "salesShare": "0.4", "salesInten": "1720680", "salesChange": "7", "salesAcc": "651302806", "audiCnt": "3042", "audiInten": "-68", "audiChange": "-2.2", "audiAcc": "77250", "scrnCnt": "67", "showCnt": "126"}]}}